evbunpack/__init__.py
evbunpack/__main__.py
evbunpack/aplib.py
evbunpack/const.py
evbunpack-0.2.5.dist-info/LICENSE
evbunpack-0.2.5.dist-info/METADATA
evbunpack-0.2.5.dist-info/WHEEL
evbunpack-0.2.5.dist-info/entry_points.txt
evbunpack-0.2.5.dist-info/top_level.txt
evbunpack-0.2.5.dist-info/RECORD
