Metadata-Version: 2.1
Name: evbunpack
Version: 0.2.5
Summary: Enigma Virtual Box Unpacker / 解包工具
Home-page: https://github.com/mos9527/evbunpack
Author: mos9527
Author-email: greats3an@gmail.com
Classifier: Programming Language :: Python :: 3
Classifier: License :: OSI Approved :: Apache Software License
Classifier: Operating System :: OS Independent
Requires-Python: >=3.0
License-File: LICENSE
Requires-Dist: pefile
